kagan/__init__.py
kagan/__main__.py
kagan/app.py
kagan/config.py
kagan/constants.py
kagan/git_utils.py
kagan/jsonrpc.py
kagan/limits.py
kagan/lock.py
kagan/theme.py
kagan/acp/__init__.py
kagan/acp/agent.py
kagan/acp/api.py
kagan/acp/buffers.py
kagan/acp/messages.py
kagan/acp/protocol.py
kagan/acp/rpc.py
kagan/acp/terminal.py
kagan/acp/terminals.py
kagan/agents/__init__.py
kagan/agents/config_resolver.py
kagan/agents/planner.py
kagan/agents/prompt.py
kagan/agents/prompt_loader.py
kagan/agents/refinement_rules.py
kagan/agents/refiner.py
kagan/agents/scheduler.py
kagan/agents/signals.py
kagan/agents/worktree.py
kagan/ansi/__init__.py
kagan/ansi/cleaner.py
kagan/cli/__init__.py
kagan/cli/update.py
kagan/data/__init__.py
kagan/data/builtin_agents.py
kagan/database/__init__.py
kagan/database/manager.py
kagan/database/models.py
kagan/database/queries.py
kagan/database/schema.sql
kagan/keybindings/__init__.py
kagan/keybindings/app.py
kagan/keybindings/kanban.py
kagan/keybindings/modals.py
kagan/keybindings/registry.py
kagan/keybindings/screens.py
kagan/keybindings/widgets.py
kagan/mcp/__init__.py
kagan/mcp/server.py
kagan/mcp/tools.py
kagan/sessions/__init__.py
kagan/sessions/manager.py
kagan/sessions/tmux.py
kagan/styles/kagan.tcss
kagan/ui/__init__.py
kagan/ui/modals/__init__.py
kagan/ui/modals/actions.py
kagan/ui/modals/agent_output.py
kagan/ui/modals/confirm.py
kagan/ui/modals/description_editor.py
kagan/ui/modals/diff.py
kagan/ui/modals/duplicate_ticket.py
kagan/ui/modals/help.py
kagan/ui/modals/rejection_input.py
kagan/ui/modals/review.py
kagan/ui/modals/settings.py
kagan/ui/modals/tmux_gateway.py
kagan/ui/modals/ticket_details/__init__.py
kagan/ui/modals/ticket_details/form.py
kagan/ui/modals/ticket_details/modal.py
kagan/ui/screens/__init__.py
kagan/ui/screens/approval.py
kagan/ui/screens/base.py
kagan/ui/screens/planner.py
kagan/ui/screens/ticket_editor.py
kagan/ui/screens/troubleshooting.py
kagan/ui/screens/welcome.py
kagan/ui/screens/kanban/__init__.py
kagan-0.2.1.dist-info/METADATA
kagan-0.2.1.dist-info/WHEEL
kagan-0.2.1.dist-info/entry_points.txt
kagan-0.2.1.dist-info/licenses/LICENSE
kagan-0.2.1.dist-info/RECORD
