Metadata-Version: 2.4
Name: kagan
Version: 0.2.1
Summary: AI-powered Kanban TUI for autonomous development workflows
Project-URL: Homepage, https://kagan.sh
Project-URL: Documentation, https://docs.kagan.sh
Project-URL: Repository, https://github.com/aorumbayev/kagan
Project-URL: Issues, https://github.com/aorumbayev/kagan/issues
Project-URL: Changelog, https://github.com/aorumbayev/kagan/blob/main/CHANGELOG.md
Author-email: Altynbek Orumbayev <altynbek.orumbayev@makerx.com.au>
License-Expression: MIT
License-File: LICENSE
Keywords: ai,autonomous,kanban,project-management,terminal,textual,tui
Classifier: Development Status :: 3 - Alpha
Classifier: Environment :: Console
Classifier: Intended Audience :: Developers
Classifier: License :: OSI Approved :: MIT License
Classifier: Operating System :: OS Independent
Classifier: Programming Language :: Python :: 3
Classifier: Programming Language :: Python :: 3.12
Classifier: Topic :: Software Development
Classifier: Topic :: Software Development :: Libraries :: Python Modules
Classifier: Topic :: Terminals
Classifier: Topic :: Utilities
Classifier: Typing :: Typed
Requires-Python: >=3.12
Requires-Dist: aiosqlite>=0.22.0
Requires-Dist: click>=8.1.0
Requires-Dist: httpx>=0.27.0
Requires-Dist: mcp>=1.0.0
Requires-Dist: packaging>=24.0
Requires-Dist: psutil>=7.0.0
Requires-Dist: pydantic>=2.10.0
Requires-Dist: pyperclip>=1.11.0
Requires-Dist: rich>=14.0.0
Requires-Dist: textual>=7.0.0
Requires-Dist: typeguard>=4.4.0
